nbdev_guide/__init__.py
nbdev_guide/_modidx.py
nbdev_guide/core.py
nbdev_guide-0.0.1.dist-info/LICENSE
nbdev_guide-0.0.1.dist-info/METADATA
nbdev_guide-0.0.1.dist-info/WHEEL
nbdev_guide-0.0.1.dist-info/entry_points.txt
nbdev_guide-0.0.1.dist-info/top_level.txt
nbdev_guide-0.0.1.dist-info/RECORD
