Metadata-Version: 2.1
Name: nbdev-guide
Version: 0.0.1
Summary: A cool python documentation.
Home-page: https://github.com/ayushmandloi2/nbdev_guide
Author: Ayush mandloi
Author-email: mandloi19faraday96@gmail.com
License: Apache Software License 2.0
Keywords: nbdev jupyter notebook python
Classifier: Development Status :: 4 - Beta
Classifier: Intended Audience :: Developers
Classifier: Natural Language :: English
Classifier: Programming Language :: Python :: 3.7
Classifier: Programming Language :: Python :: 3.8
Classifier: Programming Language :: Python :: 3.9
Classifier: Programming Language :: Python :: 3.10
Classifier: License :: OSI Approved :: Apache Software License
Requires-Python: >=3.7
License-File: LICENSE
Provides-Extra: dev
